[
    {
        "title": "All-blue Potatoes",
        "serving": "100g",
        "calories": "61 cal"
    },
    {
        "title": "Baked Potato",
        "serving": "100g",
        "calories": "93 cal"
    },
    {
        "title": "Boiled Potatoes",
        "serving": "100g",
        "calories": "87 cal"
    },
    {
        "title": "Cassava",
        "serving": "100g",
        "calories": "160 cal"
    },
    {
        "title": "Croquettes",
        "serving": "100g",
        "calories": "127 cal"
    },
    {
        "title": "Dumpling Dough",
        "serving": "100g",
        "calories": "124 cal"
    },
    {
        "title": "Dumplings",
        "serving": "100g",
        "calories": "124 cal"
    },
    {
        "title": "French Fingerling Potatoes",
        "serving": "100g",
        "calories": "82 cal"
    },
    {
        "title": "French Fries",
        "serving": "100g",
        "calories": "312 cal"
    },
    {
        "title": "Fried Potatoes",
        "serving": "100g",
        "calories": "312 cal"
    },
    {
        "title": "Gnocchi",
        "serving": "100g",
        "calories": "133 cal"
    },
    {
        "title": "Japanese Sweet Potatoes",
        "serving": "100g",
        "calories": "87 cal"
    },
    {
        "title": "Marrow Dumplings",
        "serving": "100g",
        "calories": "424 cal"
    },
    {
        "title": "Mashed Potatoes",
        "serving": "100g",
        "calories": "89 cal"
    },
    {
        "title": "Norland Red Potatoes",
        "serving": "100g",
        "calories": "89 cal"
    },
    {
        "title": "Omelette",
        "serving": "100g",
        "calories": "154 cal"
    },
    {
        "title": "Potato",
        "serving": "100g",
        "calories": "77 cal"
    },
    {
        "title": "Potato Dumpling",
        "serving": "100g",
        "calories": "124 cal"
    },
    {
        "title": "Potato Fritter",
        "serving": "100g",
        "calories": "185 cal"
    },
    {
        "title": "Potato Gratin",
        "serving": "100g",
        "calories": "132 cal"
    },
    {
        "title": "Potato Pancakes",
        "serving": "100g",
        "calories": "268 cal"
    },
    {
        "title": "Potato Salad",
        "serving": "100g",
        "calories": "143 cal"
    },
    {
        "title": "Potato Starch",
        "serving": "100g",
        "calories": "331 cal"
    },
    {
        "title": "Potato Sticks",
        "serving": "100g",
        "calories": "522 cal"
    },
    {
        "title": "Potato Waffles",
        "serving": "100g",
        "calories": "167 cal"
    },
    {
        "title": "Potato Wedges",
        "serving": "100g",
        "calories": "123 cal"
    },
    {
        "title": "Potatoes au Gratin",
        "serving": "100g",
        "calories": "132 cal"
    },
    {
        "title": "Purple Majesty Potatoes",
        "serving": "100g",
        "calories": "72 cal"
    },
    {
        "title": "Red Gold Potatoes",
        "serving": "100g",
        "calories": "89 cal"
    },
    {
        "title": "Red Potatoes",
        "serving": "100g",
        "calories": "89 cal"
    },
    {
        "title": "Roast Potatoes",
        "serving": "100g",
        "calories": "149 cal"
    },
    {
        "title": "Rosemary Potatoes",
        "serving": "100g",
        "calories": "93 cal"
    },
    {
        "title": "Rösti",
        "serving": "100g",
        "calories": "138 cal"
    },
    {
        "title": "Russet Potatoes",
        "serving": "100g",
        "calories": "97 cal"
    },
    {
        "title": "Russian Banana Potatoes",
        "serving": "100g",
        "calories": "67 cal"
    },
    {
        "title": "Sweet Potato",
        "serving": "100g",
        "calories": "92 cal"
    },
    {
        "title": "White Potatoes",
        "serving": "100g",
        "calories": "94 cal"
    },
    {
        "title": "Yams",
        "serving": "100g",
        "calories": "116 cal"
    },
    {
        "title": "Yukon Gold Potatoes",
        "serving": "100g",
        "calories": "82 cal"
    }
]